Verilog_files/decoder_again/decoder.v
`define AND and #30
`define OR or #30
`define NOT not #10
`define NAND nand #20
`define XOR xor #30
`define NOR nor #20

// module behavioralDecoder
// (
//     output out0, out1, out2, out3,
//     input address0, address1,
//     input enable
// );
//     // Uses concatenation and shift operators
//     assign {out3,out2,out1,out0}=enable<<{address1,address0};
// endmodule


module structuralDecoder
(
    output out0, out1, out2, out3,
    input address0, address1,
    input enable
);
    // Your decoder code here
    wire _address0, _address1, A, B;

    `NOT addr0inv(_address0, address0);
    `NOT addr1inv(_address1, address1);

    `AND addr1low(A, enable, _address1);
    `AND addr1low(B, enable, address1);

    `AND addr0low1low(out0, A, _address0);
    `AND addr0high1low(out1, A, address0);
    `AND addr0low1high(out2, B, _address0);
    `AND addr0high1high(out3, B, address0);
endmodule

Verilog_files/decoder_again/decoder.t.v
`timescale 1 ns / 1 ps
`include "decoder.v"

module decoder_test();

  reg address0, address1, enable;
  wire out0, out1, out2, out3;

  structuralDecoder dut(.out0(out0), .out1(out1), .out2(out2), .out3(out3),
                        .address0(address0), .address1(address1), .enable(enable));

  initial begin

    $dumpfile("decoder.vcd");
    // $dumpfile("test.vcd");
    $dumpvars(0, dut);

    $display("E A0 A1  | Q0 Q1 Q2 Q3");
    enable=1; address0=0; address1=0; #100
    $display("%d  %d  %d  |  %d  %d  %d  %d", enable, address0, address1, out0, out1, out2, out3);
    enable=1; address0=1; address1=0; #100
    $display("%d  %d  %d  |  %d  %d  %d  %d", enable, address0, address1, out0, out1, out2, out3);
    enable=1; address0=0; address1=1; #100
    $display("%d  %d  %d  |  %d  %d  %d  %d", enable, address0, address1, out0, out1, out2, out3);
    enable=1; address0=1; address1=1; #100
    $display("%d  %d  %d  |  %d  %d  %d  %d", enable, address0, address1, out0, out1, out2, out3);
    enable=0; address0=0; address1=0; #100
    $display("%d  %d  %d  |  %d  %d  %d  %d", enable, address0, address1, out0, out1, out2, out3);
    enable=0; address0=1; address1=0; #100
    $display("%d  %d  %d  |  %d  %d  %d  %d", enable, address0, address1, out0, out1, out2, out3);
    enable=0; address0=0; address1=1; #100
    $display("%d  %d  %d  |  %d  %d  %d  %d", enable, address0, address1, out0, out1, out2, out3);
    enable=0; address0=1; address1=1; #100
    $display("%d  %d  %d  |  %d  %d  %d  %d", enable, address0, address1, out0, out1, out2, out3);

  end
endmodule

Verilog_files/decoder_again/decoder.vcd
$date
	Mon Mar 19 11:22:20 2018
$end
$version
	Icarus Verilog
$end
$timescale
	1ps
$end
$scope module decoder_test $end
$scope module dut $end
$var wire 1 ! A $end
$var wire 1 " B $end
$var wire 1 # _address0 $end
$var wire 1 $ _address1 $end
$var wire 1 % address0 $end
$var wire 1 & address1 $end
$var wire 1 ' enable $end
$var wire 1 ( out0 $end
$var wire 1 ) out1 $end
$var wire 1 * out2 $end
$var wire 1 + out3 $end
$upscope $end
$upscope $end
$enddefinitions $end
#0
$dumpvars
z+
x*
z)
x(
1'
0&
0%
z$
z#
z"
x!
$end
#10000
1#
1$
#30000
0+
0)
0"
#40000
1!
#60000
0*
#70000
1(
#100000
1%
#110000
0#
#130000
1)
#140000
0(
#200000
1&
0%
#210000
0$
1#
#230000
1"
0)
#240000
0!
1(
#260000
1*
#270000
0(
#300000
1%
#310000
0#
#330000
1+
#340000
0*
#400000
0&
0%
0'
#410000
1$
1#
#430000
0+
0"
#500000
1%
#510000
0#
#600000
1&
0%
#610000
0$
1#
#700000
1%
#710000
0#
