Verilog_files/decoder_again/mux4_1.v
`define AND and #30
`define OR or #30
`define NOT not #10
`define NAND nand #20
`define XOR xor #30
`define NOR nor #20

// module behavioralMultiplexer
// (
//     output out,
//     input address0, address1,
//     input in0, in1, in2, in3
// );
//     // Join single-bit inputs into a bus, use address as index
//     wire[3:0] inputs = {in3, in2, in1, in0};
//     wire[1:0] address = {address1, address0};
//     assign out = inputs[address];
// endmodule


module structuralMultiplexer
(
    output out,
    input address0, address1,
    input in0, in1, in2, in3
);
    // Your multiplexer code here
    wire _address0, _address1, addr0010, addr0110, addr0011, addr0111;
    wire orIn0, orIn1, orIn2, orIn3;
    wire or01, or012;

    `NOT address0inv(_address0, address0);
    `NOT address0inv(_address1, address1);

    `AND addr0low1low(addr0010, _address0, _address1);
    `AND in0and(orIn0, addr0010, in0);

    `AND addr0high1low(addr0110, address0, _address1);
    `AND in0and(orIn1, addr0110, in1);

    `AND addr0low1high(addr0011, _address0, address1);
    `AND in0and(orIn2, addr0011, in2);

    `AND addr0high1high(addr0111, address0, address1);
    `AND in0and(orIn3, addr0111, in3);


    `OR output0(or01, orIn0, orIn1);
    `OR output1(or012, orIn2, or01);
    `OR output1(out, or012, orIn3);
endmodule

Verilog_files/decoder_again/mux4_1.t.v
`timescale 1 ns / 1 ps
`include "mux4_1.v"

module testMultiplexer ();
  // Your test code here
  reg address0, address1, in0, in1, in2, in3;
  wire out;

  structuralMultiplexer dut
  (
      .out(out),
      .address0(address0), .address1(address1),
      .in0(in0), .in1(in1), .in2(in2), .in3(in3)
  );

  initial begin
    $dumpfile("mux4_1.vcd");
    $dumpvars(0, dut);

    $display("Q A0 A1  | I0 I1 I2 I3");
    address0=0; address1=0; in0=0; in1=1; in2=1; in3=1;#200
    $display("%d  %d  %d  |  %d  %d  %d  %d", out, address0, address1, in0, in1, in2, in3);
    address0=0; address1=0; in0=1; in1=1; in2=1; in3=1;#200
    $display("%d  %d  %d  |  %d  %d  %d  %d", out, address0, address1, in0, in1, in2, in3);
    address0=1; address1=0; in0=1; in1=0; in2=1; in3=1;#200
    $display("%d  %d  %d  |  %d  %d  %d  %d", out, address0, address1, in0, in1, in2, in3);
    address0=1; address1=0; in0=1; in1=1; in2=1; in3=1;#200
    $display("%d  %d  %d  |  %d  %d  %d  %d", out, address0, address1, in0, in1, in2, in3);
    address0=0; address1=1; in0=1; in1=1; in2=0; in3=1;#200
    $display("%d  %d  %d  |  %d  %d  %d  %d", out, address0, address1, in0, in1, in2, in3);
    address0=0; address1=1; in0=1; in1=1; in2=1; in3=1;#200
    $display("%d  %d  %d  |  %d  %d  %d  %d", out, address0, address1, in0, in1, in2, in3);
    address0=1; address1=1; in0=1; in1=1; in2=1; in3=0;#200
    $display("%d  %d  %d  |  %d  %d  %d  %d", out, address0, address1, in0, in1, in2, in3);
    address0=1; address1=1; in0=1; in1=1; in2=1; in3=1;#200
    $display("%d  %d  %d  |  %d  %d  %d  %d", out, address0, address1, in0, in1, in2, in3);
  end


endmodule

Verilog_files/decoder_again/mux4_1.vcd
$date
	Mon Mar 19 11:40:43 2018
$end
$version
	Icarus Verilog
$end
$timescale
	1ps
$end
$scope module testMultiplexer $end
$scope module dut $end
$var wire 1 ! _address0 $end
$var wire 1 " _address1 $end
$var wire 1 # addr0010 $end
$var wire 1 $ addr0011 $end
$var wire 1 % addr0110 $end
$var wire 1 & addr0111 $end
$var wire 1 ' address0 $end
$var wire 1 ( address1 $end
$var wire 1 ) in0 $end
$var wire 1 * in1 $end
$var wire 1 + in2 $end
$var wire 1 , in3 $end
$var wire 1 - or01 $end
$var wire 1 . or012 $end
$var wire 1 / orIn0 $end
$var wire 1 0 orIn1 $end
$var wire 1 1 orIn2 $end
$var wire 1 2 orIn3 $end
$var wire 1 3 out $end
$upscope $end
$upscope $end
$enddefinitions $end
#0
$dumpvars
x3
x2
x1
x0
z/
x.
x-
1,
1+
1*
0)
0(
0'
z&
z%
z$
x#
z"
z!
$end
#10000
1!
1"
#30000
0&
0$
0%
0/
#40000
1#
#60000
02
01
00
#90000
0-
#120000
0.
#150000
03
#200000
1)
#230000
1/
#260000
1-
#290000
1.
#320000
13
#400000
0*
1'
#410000
0!
#430000
1%
#440000
0#
#470000
0/
#500000
0-
#530000
0.
#560000
03
#600000
1*
#630000
10
#660000
1-
#690000
1.
#720000
13
#800000
0+
1(
0'
#810000
0"
1!
#830000
0%
#840000
1$
#860000
00
#890000
0-
#920000
0.
#950000
03
#1000000
1+
#1030000
11
#1060000
1.
#1090000
13
#1200000
0,
1'
#1210000
0!
#1230000
1&
#1240000
0$
#1270000
01
#1300000
0.
#1330000
03
#1400000
1,
#1430000
12
#1460000
13
